Metadata-Version: 1.1
Name: yapyvcloud
Version: 0.4
Summary: yet another pyvcloud
Home-page: https://github.com/leanserpent/yapyvcloud
Author: lean.serpent
Author-email: lean.serpent@gmail.com
License: UNKNOWN
Download-URL: https://github.com/leanserpent/yapyvcloud/archive/v0.4.tar.gz
Keywords: python,vcloud
Platform: UNKNOWN
